[
  {
    "type": "postgres",
    "host": "localhost",
    "port": 5432,
    "username": "postgres",
    "password": "mysecretpassword",
    "database": "cheerful",
    "synchronize": false,
    "logging": false,
    "entities": [
      "dist/**/*.entity{.ts,.js}"
    ],
    "migrations": [
      "dist/migration/**/*.js"
    ],
    "cli": {
      "migrationsDir": "migration"
    },
    "subscribers": [
      "src/subscriber/**/*.ts"
    ]
  },
  {
    "name": "seeds",
    "type": "postgres",
    "host": "localhost",
    "port": 5432,
    "username": "postgres",
    "password": "mysecretpassword",
    "database": "cheerful",
    "synchronize": false,
    "logging": false,
    "entities": [
      "dist/**/*.entity{.ts,.js}"
    ],
    "migrations": [
      "seeds/**/*.ts"
    ],
    "cli": {
      "migrationsDir": "seeds"
    },
    "subscribers": [
      "src/subscriber/**/*.ts"
    ]
  }
]
